eztils/__init__.py
eztils/argparser.py
eztils/dict_operations.py
eztils/ezitertools.py
eztils/ezlogging.py
eztils/ezmath.py
eztils/git/__init__.py
eztils/logger.py
eztils/persistence/__init__.py
eztils/persistence/hf.py
eztils/run_parallel.py
eztils/run_parallel_os_system.py
eztils/serialization.py
eztils/structures.py
eztils/torch/__init__.py
eztils/torch/distributions.py
eztils/torch/lightning.py
eztils/torch/math.py
eztils/torch/modules.py
eztils/torch/observable.py
eztils/torch/parameters.py
eztils/torch/tensor_creators.py
eztils/torch/to.py
eztils/torch/wandb.py
eztils-0.5.0.dist-info/LICENSE
eztils-0.5.0.dist-info/METADATA
eztils-0.5.0.dist-info/WHEEL
eztils-0.5.0.dist-info/RECORD
