Metadata-Version: 2.1
Name: eztils
Version: 0.5.0
Summary: eds utilities
Home-page: https://github.com/ezhang7423/eztils
License: MIT
Author: ezhang7423
Author-email: ezhang7423@student.palomar.edu
Requires-Python: >=3.8,<4.0
Classifier: Development Status :: 3 - Alpha
Classifier: Intended Audience :: Developers
Classifier: License :: OSI Approved :: MIT License
Classifier: Operating System :: OS Independent
Classifier: Programming Language :: Python :: 3
Classifier: Programming Language :: Python :: 3.8
Classifier: Programming Language :: Python :: 3.9
Classifier: Programming Language :: Python :: 3.10
Classifier: Programming Language :: Python :: 3.11
Classifier: Programming Language :: Python :: 3.12
Classifier: Programming Language :: Python :: 3.13
Classifier: Topic :: Software Development :: Libraries :: Python Modules
Provides-Extra: persistence
Provides-Extra: torch
Requires-Dist: art (>=6.1,<7.0)
Requires-Dist: beartype (>=0.14.1,<0.18.0)
Requires-Dist: einops (>=0.6.1,<0.9.0)
Requires-Dist: ezjaxtyping (>=0.2.20,<0.3.0) ; extra == "torch"
Requires-Dist: huggingface-hub (>=0.20.3,<0.25.0) ; extra == "persistence"
Requires-Dist: loguru (>=0.7.0,<0.8.0)
Requires-Dist: numpy (==1.24.3)
Requires-Dist: nvitop (>=1.3.2,<2.0.0) ; extra == "torch"
Requires-Dist: pandas (==2.0.3)
Requires-Dist: rich (>=13.3.3,<14.0.0)
Requires-Dist: torch (>=2.2.2,<3.0.0) ; extra == "torch"
Requires-Dist: tqdm (>=4.65.0,<5.0.0)
Requires-Dist: varname (>=0.11.2,<0.14.0)
Project-URL: Repository, https://github.com/ezhang7423/eztils
